simple_multicall_v6/__init__.py
simple_multicall_v6/makerdao_multicall.py
simple_multicall_v6/multicall.py
simple_multicall_v6-0.1.6.dist-info/LICENSE
simple_multicall_v6-0.1.6.dist-info/METADATA
simple_multicall_v6-0.1.6.dist-info/WHEEL
simple_multicall_v6-0.1.6.dist-info/top_level.txt
simple_multicall_v6-0.1.6.dist-info/RECORD
