Metadata-Version: 2.1
Name: simple_multicall_v6
Version: 0.1.6
Summary: Simple Web3 multicall
Author: Chenciao8
Author-email: chenciao8@gmail.com
License: MIT
Keywords: multicall,web3
Classifier: Development Status :: 3 - Alpha
Classifier: Intended Audience :: Developers
Classifier: License :: OSI Approved :: MIT License
Classifier: Natural Language :: English
Classifier: Programming Language :: Python :: 3
Requires: Web3
License-File: LICENSE
